{
  "parent": "minecraft:recipes/root",
  "rewards": {
    "recipes": [
      "kingdomkeys:pure_heart"
    ]
  },
  "criteria": {
    "heart": {
      "trigger": "minecraft:inventory_changed",
      "conditions": {
        "items": [
          {
            "item": "kingdomkeys:heart"
          }
        ]
      }
    },
    "has_the_recipe": {
      "trigger": "minecraft:recipe_unlocked",
      "conditions": {
        "recipe": "kingdomkeys:pure_heart"
      }
    }
  },
  "requirements": [
    [
      "heart",
      "has_the_recipe"
    ]
  ]
}