{
  "parent": "minecraft:recipes/root",
  "criteria": {
    "ava_chestplate": {
      "conditions": {
        "items": [
          {
            "items": [
              "kingdomkeys:ava_chestplate"
            ]
          }
        ]
      },
      "trigger": "minecraft:inventory_changed"
    },
    "has_the_recipe": {
      "conditions": {
        "recipe": "kingdomkeys:gula_chestplate"
      },
      "trigger": "minecraft:recipe_unlocked"
    }
  },
  "requirements": [
    [
      "ava_chestplate",
      "has_the_recipe"
    ]
  ],
  "rewards": {
    "recipes": [
      "kingdomkeys:gula_chestplate"
    ]
  }
}