{
  "parent": "minecraft:recipes/root",
  "rewards": {
    "recipes": [
      "kingdomkeys:invi_boots"
    ]
  },
  "criteria": {
    "gula_boots": {
      "trigger": "minecraft:inventory_changed",
      "conditions": {
        "items": [
          {
            "item": "kingdomkeys:gula_boots"
          }
        ]
      }
    },
    "has_the_recipe": {
      "trigger": "minecraft:recipe_unlocked",
      "conditions": {
        "recipe": "kingdomkeys:invi_boots"
      }
    }
  },
  "requirements": [
    [
      "gula_boots",
      "has_the_recipe"
    ]
  ]
}